[
    {
        "french": "archéoastronomie",
        "english": "archaeoastronomy"
    },
    {
        "french": "archéologie sous-marine",
        "english": "underwater archaeology"
    },
    {
        "french": "archéologie urbaine",
        "english": "urban archaeology"
    },
    {
        "french": "archéologie industrielle",
        "english": "industrial archaeology"
    },
    {
        "french": "archéologie médiévale",
        "english": "medieval archaeology"
    },
    {
        "french": "archéologie préhistorique",
        "english": "prehistoric archaeology"
    },
    {
        "french": "archéologie classique",
        "english": "classical archaeology"
    },
    {
        "french": "archéologie historique",
        "english": "historical archaeology"
    },
    {
        "french": "archéologie expérimentale",
        "english": "experimental archaeology"
    },
    {
        "french": "archéologie sociale",
        "english": "social archaeology"
    },
    {
        "french": "archéologie cognitive",
        "english": "cognitive archaeology"
    },
    {
        "french": "archéologie digitale",
        "english": "digital archaeology"
    },
    {
        "french": "archéologie du patrimoine",
        "english": "heritage archaeology"
    },
    {
        "french": "archéologie maritime",
        "english": "maritime archaeology"
    },
    {
        "french": "archéologie de la guerre",
        "english": "war archaeology"
    },
    {
        "french": "archéologie post-moderne",
        "english": "post-modern archaeology"
    },
    {
        "french": "archéologie environnementale",
        "english": "environmental archaeology"
    },
    {
        "french": "archéologie régionale",
        "english": "regional archaeology"
    },
    {
        "french": "archéologie transdisciplinaire",
        "english": "transdisciplinary archaeology"
    },
    {
        "french": "archéologie comparative",
        "english": "comparative archaeology"
    },
    {
        "french": "archéologie historique",
        "english": "historical archaeology"
    }
]